implica-1.1.7.dist-info/METADATA
implica-1.1.7.dist-info/WHEEL
implica-1.1.7.dist-info/licenses/LICENSE
implica.libs/libgcc_s-6d2d9dc8.so.1
implica/__init__.py
implica/__init__.pyi
implica/implica.abi3.so
implica/py.typed
implica-1.1.7.dist-info/RECORD
